{"cameraMode":{"drawMode":0,"name":"Shaded","section":"Shading Mode"},"sceneLighting":false,"audioPlay":false,"sceneViewState":{"showFog":true,"showMaterialUpdate":false,"showSkybox":false,"showFlares":true,"showImageEffects":true,"showParticleSystems":true},"in2DMode":false,"pivot":{"x":360.6843566894531,"y":33.34272766113281,"z":422.9374694824219},"rotation":{"x":-0.004406101536005735,"y":0.994185209274292,"z":-0.04476853087544441,"w":-0.09784522652626038},"size":2.1813881397247316,"orthographic":false}